pysitemaps/__init__.py
pysitemaps-0.0.6.dist-info/LICENSE
pysitemaps-0.0.6.dist-info/METADATA
pysitemaps-0.0.6.dist-info/WHEEL
pysitemaps-0.0.6.dist-info/top_level.txt
pysitemaps-0.0.6.dist-info/RECORD
